clean_h1b/__init__.py
clean_h1b/data_clean.py
h1b_processor-1.73.dist-info/LICENSE
h1b_processor-1.73.dist-info/METADATA
h1b_processor-1.73.dist-info/WHEEL
h1b_processor-1.73.dist-info/top_level.txt
h1b_processor-1.73.dist-info/RECORD
