Metadata-Version: 2.1
Name: h1b_processor
Version: 1.73
Summary: A package for cleaning data frames.
Home-page: https://github.com/AravindSatyan/data-warehousing/tree/main
Author: Aravind Satyanarayanan
Author-email: aravind.bedean@gmail.com
Classifier: Programming Language :: Python :: 3
Classifier: License :: OSI Approved :: MIT License
Classifier: Operating System :: OS Independent
Requires-Python: >=3.6
License-File: LICENSE
Requires-Dist: pandas
Requires-Dist: requests
Requires-Dist: beautifulsoup4
Requires-Dist: tqdm
